Metadata-Version: 2.4
Name: shapeedit
Version: 0.5.0b3
Summary: A library that provides experimental operations for modifying existing MSTS/ORTS shape files.
Author: Peter Grønbæk Andersen
Author-email: Peter Grønbæk Andersen <peter@grnbk.io>
License: GNU GPL v3
Project-URL: Homepage, https://github.com/pgroenbaek/shapeedit
Project-URL: Issues, https://github.com/pgroenbaek/shapeedit/issues
Project-URL: Source, https://github.com/pgroenbaek/shapeedit
Classifier: Programming Language :: Python :: 3
Classifier: License :: OSI Approved :: GNU General Public License v3 or later (GPLv3+)
Classifier: Operating System :: OS Independent
Requires-Python: >=3.7
Requires-Dist: numpy
Requires-Dist: shapeio==0.5.0b3
Dynamic: author
Dynamic: requires-python
